haystack_integrations/components/retrievers/py.typed
haystack_integrations/components/retrievers/chroma/__init__.py
haystack_integrations/components/retrievers/chroma/retriever.py
haystack_integrations/document_stores/py.typed
haystack_integrations/document_stores/chroma/__init__.py
haystack_integrations/document_stores/chroma/document_store.py
haystack_integrations/document_stores/chroma/errors.py
haystack_integrations/document_stores/chroma/filters.py
haystack_integrations/document_stores/chroma/utils.py
chroma_haystack-3.4.1.dist-info/METADATA
chroma_haystack-3.4.1.dist-info/WHEEL
chroma_haystack-3.4.1.dist-info/licenses/LICENSE
chroma_haystack-3.4.1.dist-info/RECORD
