Metadata-Version: 2.4
Name: chroma-haystack
Version: 3.4.1
Project-URL: Documentation, https://github.com/deepset-ai/haystack-core-integrations/tree/main/integrations/chroma#readme
Project-URL: Issues, https://github.com/deepset-ai/haystack-core-integrations/issues
Project-URL: Source, https://github.com/deepset-ai/haystack-core-integrations/tree/main/integrations/chroma
Author-email: John Doe <jd@example.com>
License-Expression: Apache-2.0
License-File: LICENSE
Classifier: Development Status :: 4 - Beta
Classifier: License :: OSI Approved :: Apache Software License
Classifier: Programming Language :: Python
Classifier: Programming Language :: Python :: 3.9
Classifier: Programming Language :: Python :: 3.10
Classifier: Programming Language :: Python :: 3.11
Classifier: Programming Language :: Python :: 3.12
Classifier: Programming Language :: Python :: 3.13
Classifier: Programming Language :: Python :: Implementation :: CPython
Classifier: Programming Language :: Python :: Implementation :: PyPy
Requires-Python: >=3.9
Requires-Dist: chromadb>=1.0.2
Requires-Dist: haystack-ai>=2.11.0
